carton/__init__.py
carton/cart.py
carton/models.py
carton/module_loading.py
carton/settings.py
carton/templatetags/__init__.py
carton/templatetags/carton_tags.py
carton/tests/__init__.py
carton/tests/models.py
carton/tests/settings.py
carton/tests/tests.py
carton/tests/urls.py
carton/tests/views.py
engiwiz_django_carton-1.2.2.dist-info/LICENSE
engiwiz_django_carton-1.2.2.dist-info/METADATA
engiwiz_django_carton-1.2.2.dist-info/WHEEL
engiwiz_django_carton-1.2.2.dist-info/top_level.txt
engiwiz_django_carton-1.2.2.dist-info/RECORD
